[
  {
    "src_svg": "/home/darren/icon-retrieval/icons-dynamic/remix-weather/remix-weather:blaze-fill.svg",
    "component_id": "Icon.RemixWeather:BlazeFill",
    "aliases": [
      "remix",
      "weather:blaze",
      "fill"
    ],
    "caption": "a black background with an airplane flying in the air",
    "colors": []
  },
  {
    "src_svg": "/home/darren/icon-retrieval/icons-dynamic/remix-weather/remix-weather:blaze-line.svg",
    "component_id": "Icon.RemixWeather:BlazeLine",
    "aliases": [
      "remix",
      "weather:blaze",
      "line"
    ],
    "caption": "a black background with an airplane flying in the air",
    "colors": []
  },
  {
    "src_svg": "/home/darren/icon-retrieval/icons-dynamic/remix-weather/remix-weather:celsius-fill.svg",
    "component_id": "Icon.RemixWeather:CelsiusFill",
    "aliases": [
      "remix",
      "weather:celsius",
      "fill"
    ],
    "caption": "a black background with an airplane flying in the air",
    "colors": []
  },
  {
    "src_svg": "/home/darren/icon-retrieval/icons-dynamic/remix-weather/remix-weather:celsius-line.svg",
    "component_id": "Icon.RemixWeather:CelsiusLine",
    "aliases": [
      "remix",
      "weather:celsius",
      "line"
    ],
    "caption": "a black background with an airplane flying in the air",
    "colors": []
  },
  {
    "src_svg": "/home/darren/icon-retrieval/icons-dynamic/remix-weather/remix-weather:cloud-windy-fill.svg",
    "component_id": "Icon.RemixWeather:CloudWindyFill",
    "aliases": [
      "remix",
      "weather:cloud",
      "windy",
      "fill"
    ],
    "caption": "a black background with an airplane flying in the air",
    "colors": []
  },
  {
    "src_svg": "/home/darren/icon-retrieval/icons-dynamic/remix-weather/remix-weather:cloud-windy-line.svg",
    "component_id": "Icon.RemixWeather:CloudWindyLine",
    "aliases": [
      "remix",
      "weather:cloud",
      "windy",
      "line"
    ],
    "caption": "a black background with an airplane flying in the air",
    "colors": []
  },
  {
    "src_svg": "/home/darren/icon-retrieval/icons-dynamic/remix-weather/remix-weather:cloudy-2-fill.svg",
    "component_id": "Icon.RemixWeather:Cloudy2Fill",
    "aliases": [
      "remix",
      "weather:cloudy",
      "2",
      "fill"
    ],
    "caption": "a black background with an airplane flying in the air",
    "colors": []
  },
  {
    "src_svg": "/home/darren/icon-retrieval/icons-dynamic/remix-weather/remix-weather:cloudy-2-line.svg",
    "component_id": "Icon.RemixWeather:Cloudy2Line",
    "aliases": [
      "remix",
      "weather:cloudy",
      "2",
      "line"
    ],
    "caption": "a black background with an airplane flying in the air",
    "colors": []
  },
  {
    "src_svg": "/home/darren/icon-retrieval/icons-dynamic/remix-weather/remix-weather:cloudy-fill.svg",
    "component_id": "Icon.RemixWeather:CloudyFill",
    "aliases": [
      "remix",
      "weather:cloudy",
      "fill"
    ],
    "caption": "a black background with an airplane flying in the air",
    "colors": []
  },
  {
    "src_svg": "/home/darren/icon-retrieval/icons-dynamic/remix-weather/remix-weather:cloudy-line.svg",
    "component_id": "Icon.RemixWeather:CloudyLine",
    "aliases": [
      "remix",
      "weather:cloudy",
      "line"
    ],
    "caption": "a black background with an airplane flying in the air",
    "colors": []
  },
  {
    "src_svg": "/home/darren/icon-retrieval/icons-dynamic/remix-weather/remix-weather:drizzle-fill.svg",
    "component_id": "Icon.RemixWeather:DrizzleFill",
    "aliases": [
      "remix",
      "weather:drizzle",
      "fill"
    ],
    "caption": "a black background with an airplane flying in the air",
    "colors": []
  },
  {
    "src_svg": "/home/darren/icon-retrieval/icons-dynamic/remix-weather/remix-weather:drizzle-line.svg",
    "component_id": "Icon.RemixWeather:DrizzleLine",
    "aliases": [
      "remix",
      "weather:drizzle",
      "line"
    ],
    "caption": "a black background with an airplane flying in the air",
    "colors": []
  },
  {
    "src_svg": "/home/darren/icon-retrieval/icons-dynamic/remix-weather/remix-weather:earthquake-fill.svg",
    "component_id": "Icon.RemixWeather:EarthquakeFill",
    "aliases": [
      "remix",
      "weather:earthquake",
      "fill"
    ],
    "caption": "a black background with an airplane flying in the air",
    "colors": []
  },
  {
    "src_svg": "/home/darren/icon-retrieval/icons-dynamic/remix-weather/remix-weather:earthquake-line.svg",
    "component_id": "Icon.RemixWeather:EarthquakeLine",
    "aliases": [
      "remix",
      "weather:earthquake",
      "line"
    ],
    "caption": "a black background with an airplane flying in the air",
    "colors": []
  },
  {
    "src_svg": "/home/darren/icon-retrieval/icons-dynamic/remix-weather/remix-weather:fahrenheit-fill.svg",
    "component_id": "Icon.RemixWeather:FahrenheitFill",
    "aliases": [
      "remix",
      "weather:fahrenheit",
      "fill"
    ],
    "caption": "a black background with an airplane flying in the air",
    "colors": []
  },
  {
    "src_svg": "/home/darren/icon-retrieval/icons-dynamic/remix-weather/remix-weather:fahrenheit-line.svg",
    "component_id": "Icon.RemixWeather:FahrenheitLine",
    "aliases": [
      "remix",
      "weather:fahrenheit",
      "line"
    ],
    "caption": "a black background with an airplane flying in the air",
    "colors": []
  },
  {
    "src_svg": "/home/darren/icon-retrieval/icons-dynamic/remix-weather/remix-weather:fire-fill.svg",
    "component_id": "Icon.RemixWeather:FireFill",
    "aliases": [
      "remix",
      "weather:fire",
      "fill"
    ],
    "caption": "a black background with an airplane flying in the air",
    "colors": []
  },
  {
    "src_svg": "/home/darren/icon-retrieval/icons-dynamic/remix-weather/remix-weather:fire-line.svg",
    "component_id": "Icon.RemixWeather:FireLine",
    "aliases": [
      "remix",
      "weather:fire",
      "line"
    ],
    "caption": "a black background with an airplane flying in the air",
    "colors": []
  },
  {
    "src_svg": "/home/darren/icon-retrieval/icons-dynamic/remix-weather/remix-weather:flashlight-fill.svg",
    "component_id": "Icon.RemixWeather:FlashlightFill",
    "aliases": [
      "remix",
      "weather:flashlight",
      "fill"
    ],
    "caption": "a black background with an airplane flying in the air",
    "colors": []
  },
  {
    "src_svg": "/home/darren/icon-retrieval/icons-dynamic/remix-weather/remix-weather:flashlight-line.svg",
    "component_id": "Icon.RemixWeather:FlashlightLine",
    "aliases": [
      "remix",
      "weather:flashlight",
      "line"
    ],
    "caption": "a black background with an airplane flying in the air",
    "colors": []
  },
  {
    "src_svg": "/home/darren/icon-retrieval/icons-dynamic/remix-weather/remix-weather:flood-fill.svg",
    "component_id": "Icon.RemixWeather:FloodFill",
    "aliases": [
      "remix",
      "weather:flood",
      "fill"
    ],
    "caption": "a black background with an airplane flying in the air",
    "colors": []
  },
  {
    "src_svg": "/home/darren/icon-retrieval/icons-dynamic/remix-weather/remix-weather:flood-line.svg",
    "component_id": "Icon.RemixWeather:FloodLine",
    "aliases": [
      "remix",
      "weather:flood",
      "line"
    ],
    "caption": "a black background with an airplane flying in the air",
    "colors": []
  },
  {
    "src_svg": "/home/darren/icon-retrieval/icons-dynamic/remix-weather/remix-weather:foggy-fill.svg",
    "component_id": "Icon.RemixWeather:FoggyFill",
    "aliases": [
      "remix",
      "weather:foggy",
      "fill"
    ],
    "caption": "a black background with an airplane flying in the air",
    "colors": []
  },
  {
    "src_svg": "/home/darren/icon-retrieval/icons-dynamic/remix-weather/remix-weather:foggy-line.svg",
    "component_id": "Icon.RemixWeather:FoggyLine",
    "aliases": [
      "remix",
      "weather:foggy",
      "line"
    ],
    "caption": "a black background with an airplane flying in the air",
    "colors": []
  },
  {
    "src_svg": "/home/darren/icon-retrieval/icons-dynamic/remix-weather/remix-weather:hail-fill.svg",
    "component_id": "Icon.RemixWeather:HailFill",
    "aliases": [
      "remix",
      "weather:hail",
      "fill"
    ],
    "caption": "a black background with an airplane flying in the air",
    "colors": []
  },
  {
    "src_svg": "/home/darren/icon-retrieval/icons-dynamic/remix-weather/remix-weather:hail-line.svg",
    "component_id": "Icon.RemixWeather:HailLine",
    "aliases": [
      "remix",
      "weather:hail",
      "line"
    ],
    "caption": "a black background with an airplane flying in the air",
    "colors": []
  },
  {
    "src_svg": "/home/darren/icon-retrieval/icons-dynamic/remix-weather/remix-weather:haze-2-fill.svg",
    "component_id": "Icon.RemixWeather:Haze2Fill",
    "aliases": [
      "remix",
      "weather:haze",
      "2",
      "fill"
    ],
    "caption": "a black background with an airplane flying in the air",
    "colors": []
  },
  {
    "src_svg": "/home/darren/icon-retrieval/icons-dynamic/remix-weather/remix-weather:haze-2-line.svg",
    "component_id": "Icon.RemixWeather:Haze2Line",
    "aliases": [
      "remix",
      "weather:haze",
      "2",
      "line"
    ],
    "caption": "a black background with an airplane flying in the air",
    "colors": []
  },
  {
    "src_svg": "/home/darren/icon-retrieval/icons-dynamic/remix-weather/remix-weather:haze-fill.svg",
    "component_id": "Icon.RemixWeather:HazeFill",
    "aliases": [
      "remix",
      "weather:haze",
      "fill"
    ],
    "caption": "a black background with an airplane flying in the air",
    "colors": []
  },
  {
    "src_svg": "/home/darren/icon-retrieval/icons-dynamic/remix-weather/remix-weather:haze-line.svg",
    "component_id": "Icon.RemixWeather:HazeLine",
    "aliases": [
      "remix",
      "weather:haze",
      "line"
    ],
    "caption": "a black background with an airplane flying in the air",
    "colors": []
  },
  {
    "src_svg": "/home/darren/icon-retrieval/icons-dynamic/remix-weather/remix-weather:heavy-showers-fill.svg",
    "component_id": "Icon.RemixWeather:HeavyShowersFill",
    "aliases": [
      "remix",
      "weather:heavy",
      "showers",
      "fill"
    ],
    "caption": "a black background with an airplane flying in the air",
    "colors": []
  },
  {
    "src_svg": "/home/darren/icon-retrieval/icons-dynamic/remix-weather/remix-weather:heavy-showers-line.svg",
    "component_id": "Icon.RemixWeather:HeavyShowersLine",
    "aliases": [
      "remix",
      "weather:heavy",
      "showers",
      "line"
    ],
    "caption": "a black background with an airplane flying in the air",
    "colors": []
  },
  {
    "src_svg": "/home/darren/icon-retrieval/icons-dynamic/remix-weather/remix-weather:meteor-fill.svg",
    "component_id": "Icon.RemixWeather:MeteorFill",
    "aliases": [
      "remix",
      "weather:meteor",
      "fill"
    ],
    "caption": "a black background with an airplane flying in the air",
    "colors": []
  },
  {
    "src_svg": "/home/darren/icon-retrieval/icons-dynamic/remix-weather/remix-weather:meteor-line.svg",
    "component_id": "Icon.RemixWeather:MeteorLine",
    "aliases": [
      "remix",
      "weather:meteor",
      "line"
    ],
    "caption": "a black background with an airplane flying in the air",
    "colors": []
  },
  {
    "src_svg": "/home/darren/icon-retrieval/icons-dynamic/remix-weather/remix-weather:mist-fill.svg",
    "component_id": "Icon.RemixWeather:MistFill",
    "aliases": [
      "remix",
      "weather:mist",
      "fill"
    ],
    "caption": "a black background with an airplane flying in the air",
    "colors": []
  },
  {
    "src_svg": "/home/darren/icon-retrieval/icons-dynamic/remix-weather/remix-weather:mist-line.svg",
    "component_id": "Icon.RemixWeather:MistLine",
    "aliases": [
      "remix",
      "weather:mist",
      "line"
    ],
    "caption": "a black background with an airplane flying in the air",
    "colors": []
  },
  {
    "src_svg": "/home/darren/icon-retrieval/icons-dynamic/remix-weather/remix-weather:moon-clear-fill.svg",
    "component_id": "Icon.RemixWeather:MoonClearFill",
    "aliases": [
      "remix",
      "weather:moon",
      "clear",
      "fill"
    ],
    "caption": "a black background with an airplane flying in the air",
    "colors": []
  },
  {
    "src_svg": "/home/darren/icon-retrieval/icons-dynamic/remix-weather/remix-weather:moon-clear-line.svg",
    "component_id": "Icon.RemixWeather:MoonClearLine",
    "aliases": [
      "remix",
      "weather:moon",
      "clear",
      "line"
    ],
    "caption": "a black background with an airplane flying in the air",
    "colors": []
  },
  {
    "src_svg": "/home/darren/icon-retrieval/icons-dynamic/remix-weather/remix-weather:moon-cloudy-fill.svg",
    "component_id": "Icon.RemixWeather:MoonCloudyFill",
    "aliases": [
      "remix",
      "weather:moon",
      "cloudy",
      "fill"
    ],
    "caption": "a black background with an airplane flying in the air",
    "colors": []
  },
  {
    "src_svg": "/home/darren/icon-retrieval/icons-dynamic/remix-weather/remix-weather:moon-cloudy-line.svg",
    "component_id": "Icon.RemixWeather:MoonCloudyLine",
    "aliases": [
      "remix",
      "weather:moon",
      "cloudy",
      "line"
    ],
    "caption": "a black background with an airplane flying in the air",
    "colors": []
  },
  {
    "src_svg": "/home/darren/icon-retrieval/icons-dynamic/remix-weather/remix-weather:moon-fill.svg",
    "component_id": "Icon.RemixWeather:MoonFill",
    "aliases": [
      "remix",
      "weather:moon",
      "fill"
    ],
    "caption": "a black background with an airplane flying in the air",
    "colors": []
  },
  {
    "src_svg": "/home/darren/icon-retrieval/icons-dynamic/remix-weather/remix-weather:moon-foggy-fill.svg",
    "component_id": "Icon.RemixWeather:MoonFoggyFill",
    "aliases": [
      "remix",
      "weather:moon",
      "foggy",
      "fill"
    ],
    "caption": "a black background with an airplane flying in the air",
    "colors": []
  },
  {
    "src_svg": "/home/darren/icon-retrieval/icons-dynamic/remix-weather/remix-weather:moon-foggy-line.svg",
    "component_id": "Icon.RemixWeather:MoonFoggyLine",
    "aliases": [
      "remix",
      "weather:moon",
      "foggy",
      "line"
    ],
    "caption": "a black background with an airplane flying in the air",
    "colors": []
  },
  {
    "src_svg": "/home/darren/icon-retrieval/icons-dynamic/remix-weather/remix-weather:moon-line.svg",
    "component_id": "Icon.RemixWeather:MoonLine",
    "aliases": [
      "remix",
      "weather:moon",
      "line"
    ],
    "caption": "a black background with an airplane flying in the air",
    "colors": []
  },
  {
    "src_svg": "/home/darren/icon-retrieval/icons-dynamic/remix-weather/remix-weather:rainbow-fill.svg",
    "component_id": "Icon.RemixWeather:RainbowFill",
    "aliases": [
      "remix",
      "weather:rainbow",
      "fill"
    ],
    "caption": "a black background with an airplane flying in the air",
    "colors": []
  },
  {
    "src_svg": "/home/darren/icon-retrieval/icons-dynamic/remix-weather/remix-weather:rainbow-line.svg",
    "component_id": "Icon.RemixWeather:RainbowLine",
    "aliases": [
      "remix",
      "weather:rainbow",
      "line"
    ],
    "caption": "a black background with an airplane flying in the air",
    "colors": []
  },
  {
    "src_svg": "/home/darren/icon-retrieval/icons-dynamic/remix-weather/remix-weather:rainy-fill.svg",
    "component_id": "Icon.RemixWeather:RainyFill",
    "aliases": [
      "remix",
      "weather:rainy",
      "fill"
    ],
    "caption": "a black background with an airplane flying in the air",
    "colors": []
  },
  {
    "src_svg": "/home/darren/icon-retrieval/icons-dynamic/remix-weather/remix-weather:rainy-line.svg",
    "component_id": "Icon.RemixWeather:RainyLine",
    "aliases": [
      "remix",
      "weather:rainy",
      "line"
    ],
    "caption": "a black background with an airplane flying in the air",
    "colors": []
  },
  {
    "src_svg": "/home/darren/icon-retrieval/icons-dynamic/remix-weather/remix-weather:shining-2-fill.svg",
    "component_id": "Icon.RemixWeather:Shining2Fill",
    "aliases": [
      "remix",
      "weather:shining",
      "2",
      "fill"
    ],
    "caption": "a black background with an airplane flying in the air",
    "colors": []
  },
  {
    "src_svg": "/home/darren/icon-retrieval/icons-dynamic/remix-weather/remix-weather:shining-2-line.svg",
    "component_id": "Icon.RemixWeather:Shining2Line",
    "aliases": [
      "remix",
      "weather:shining",
      "2",
      "line"
    ],
    "caption": "a black background with an airplane flying in the air",
    "colors": []
  },
  {
    "src_svg": "/home/darren/icon-retrieval/icons-dynamic/remix-weather/remix-weather:shining-fill.svg",
    "component_id": "Icon.RemixWeather:ShiningFill",
    "aliases": [
      "remix",
      "weather:shining",
      "fill"
    ],
    "caption": "a black background with an airplane flying in the air",
    "colors": []
  },
  {
    "src_svg": "/home/darren/icon-retrieval/icons-dynamic/remix-weather/remix-weather:shining-line.svg",
    "component_id": "Icon.RemixWeather:ShiningLine",
    "aliases": [
      "remix",
      "weather:shining",
      "line"
    ],
    "caption": "a black background with an airplane flying in the air",
    "colors": []
  },
  {
    "src_svg": "/home/darren/icon-retrieval/icons-dynamic/remix-weather/remix-weather:showers-fill.svg",
    "component_id": "Icon.RemixWeather:ShowersFill",
    "aliases": [
      "remix",
      "weather:showers",
      "fill"
    ],
    "caption": "a black background with an airplane flying in the air",
    "colors": []
  },
  {
    "src_svg": "/home/darren/icon-retrieval/icons-dynamic/remix-weather/remix-weather:showers-line.svg",
    "component_id": "Icon.RemixWeather:ShowersLine",
    "aliases": [
      "remix",
      "weather:showers",
      "line"
    ],
    "caption": "a black background with an airplane flying in the air",
    "colors": []
  },
  {
    "src_svg": "/home/darren/icon-retrieval/icons-dynamic/remix-weather/remix-weather:snowflake-fill.svg",
    "component_id": "Icon.RemixWeather:SnowflakeFill",
    "aliases": [
      "remix",
      "weather:snowflake",
      "fill"
    ],
    "caption": "a black background with an airplane flying in the air",
    "colors": []
  },
  {
    "src_svg": "/home/darren/icon-retrieval/icons-dynamic/remix-weather/remix-weather:snowflake-line.svg",
    "component_id": "Icon.RemixWeather:SnowflakeLine",
    "aliases": [
      "remix",
      "weather:snowflake",
      "line"
    ],
    "caption": "a black background with an airplane flying in the air",
    "colors": []
  },
  {
    "src_svg": "/home/darren/icon-retrieval/icons-dynamic/remix-weather/remix-weather:snowy-fill.svg",
    "component_id": "Icon.RemixWeather:SnowyFill",
    "aliases": [
      "remix",
      "weather:snowy",
      "fill"
    ],
    "caption": "a black background with an airplane flying in the air",
    "colors": []
  },
  {
    "src_svg": "/home/darren/icon-retrieval/icons-dynamic/remix-weather/remix-weather:snowy-line.svg",
    "component_id": "Icon.RemixWeather:SnowyLine",
    "aliases": [
      "remix",
      "weather:snowy",
      "line"
    ],
    "caption": "a black background with an airplane flying in the air",
    "colors": []
  },
  {
    "src_svg": "/home/darren/icon-retrieval/icons-dynamic/remix-weather/remix-weather:sparkling-2-fill.svg",
    "component_id": "Icon.RemixWeather:Sparkling2Fill",
    "aliases": [
      "remix",
      "weather:sparkling",
      "2",
      "fill"
    ],
    "caption": "a black background with an airplane flying in the air",
    "colors": []
  },
  {
    "src_svg": "/home/darren/icon-retrieval/icons-dynamic/remix-weather/remix-weather:sparkling-2-line.svg",
    "component_id": "Icon.RemixWeather:Sparkling2Line",
    "aliases": [
      "remix",
      "weather:sparkling",
      "2",
      "line"
    ],
    "caption": "a black background with an airplane flying in the air",
    "colors": []
  },
  {
    "src_svg": "/home/darren/icon-retrieval/icons-dynamic/remix-weather/remix-weather:sparkling-fill.svg",
    "component_id": "Icon.RemixWeather:SparklingFill",
    "aliases": [
      "remix",
      "weather:sparkling",
      "fill"
    ],
    "caption": "a black background with an airplane flying in the air",
    "colors": []
  },
  {
    "src_svg": "/home/darren/icon-retrieval/icons-dynamic/remix-weather/remix-weather:sparkling-line.svg",
    "component_id": "Icon.RemixWeather:SparklingLine",
    "aliases": [
      "remix",
      "weather:sparkling",
      "line"
    ],
    "caption": "a black background with an airplane flying in the air",
    "colors": []
  },
  {
    "src_svg": "/home/darren/icon-retrieval/icons-dynamic/remix-weather/remix-weather:sun-cloudy-fill.svg",
    "component_id": "Icon.RemixWeather:SunCloudyFill",
    "aliases": [
      "remix",
      "weather:sun",
      "cloudy",
      "fill"
    ],
    "caption": "a black background with an airplane flying in the air",
    "colors": []
  },
  {
    "src_svg": "/home/darren/icon-retrieval/icons-dynamic/remix-weather/remix-weather:sun-cloudy-line.svg",
    "component_id": "Icon.RemixWeather:SunCloudyLine",
    "aliases": [
      "remix",
      "weather:sun",
      "cloudy",
      "line"
    ],
    "caption": "a black background with an airplane flying in the air",
    "colors": []
  },
  {
    "src_svg": "/home/darren/icon-retrieval/icons-dynamic/remix-weather/remix-weather:sun-fill.svg",
    "component_id": "Icon.RemixWeather:SunFill",
    "aliases": [
      "remix",
      "weather:sun",
      "fill"
    ],
    "caption": "a black background with an airplane flying in the air",
    "colors": []
  },
  {
    "src_svg": "/home/darren/icon-retrieval/icons-dynamic/remix-weather/remix-weather:sun-foggy-fill.svg",
    "component_id": "Icon.RemixWeather:SunFoggyFill",
    "aliases": [
      "remix",
      "weather:sun",
      "foggy",
      "fill"
    ],
    "caption": "a black background with an airplane flying in the air",
    "colors": []
  },
  {
    "src_svg": "/home/darren/icon-retrieval/icons-dynamic/remix-weather/remix-weather:sun-foggy-line.svg",
    "component_id": "Icon.RemixWeather:SunFoggyLine",
    "aliases": [
      "remix",
      "weather:sun",
      "foggy",
      "line"
    ],
    "caption": "a black background with an airplane flying in the air",
    "colors": []
  },
  {
    "src_svg": "/home/darren/icon-retrieval/icons-dynamic/remix-weather/remix-weather:sun-line.svg",
    "component_id": "Icon.RemixWeather:SunLine",
    "aliases": [
      "remix",
      "weather:sun",
      "line"
    ],
    "caption": "a black background with an airplane flying in the air",
    "colors": []
  },
  {
    "src_svg": "/home/darren/icon-retrieval/icons-dynamic/remix-weather/remix-weather:temp-cold-fill.svg",
    "component_id": "Icon.RemixWeather:TempColdFill",
    "aliases": [
      "remix",
      "weather:temp",
      "cold",
      "fill"
    ],
    "caption": "a black background with an airplane flying in the air",
    "colors": []
  },
  {
    "src_svg": "/home/darren/icon-retrieval/icons-dynamic/remix-weather/remix-weather:temp-cold-line.svg",
    "component_id": "Icon.RemixWeather:TempColdLine",
    "aliases": [
      "remix",
      "weather:temp",
      "cold",
      "line"
    ],
    "caption": "a black background with an airplane flying in the air",
    "colors": []
  },
  {
    "src_svg": "/home/darren/icon-retrieval/icons-dynamic/remix-weather/remix-weather:temp-hot-fill.svg",
    "component_id": "Icon.RemixWeather:TempHotFill",
    "aliases": [
      "remix",
      "weather:temp",
      "hot",
      "fill"
    ],
    "caption": "a black background with an airplane flying in the air",
    "colors": []
  },
  {
    "src_svg": "/home/darren/icon-retrieval/icons-dynamic/remix-weather/remix-weather:temp-hot-line.svg",
    "component_id": "Icon.RemixWeather:TempHotLine",
    "aliases": [
      "remix",
      "weather:temp",
      "hot",
      "line"
    ],
    "caption": "a black background with an airplane flying in the air",
    "colors": []
  },
  {
    "src_svg": "/home/darren/icon-retrieval/icons-dynamic/remix-weather/remix-weather:thunderstorms-fill.svg",
    "component_id": "Icon.RemixWeather:ThunderstormsFill",
    "aliases": [
      "remix",
      "weather:thunderstorms",
      "fill"
    ],
    "caption": "a black background with an airplane flying in the air",
    "colors": []
  },
  {
    "src_svg": "/home/darren/icon-retrieval/icons-dynamic/remix-weather/remix-weather:thunderstorms-line.svg",
    "component_id": "Icon.RemixWeather:ThunderstormsLine",
    "aliases": [
      "remix",
      "weather:thunderstorms",
      "line"
    ],
    "caption": "a black background with an airplane flying in the air",
    "colors": []
  },
  {
    "src_svg": "/home/darren/icon-retrieval/icons-dynamic/remix-weather/remix-weather:tornado-fill.svg",
    "component_id": "Icon.RemixWeather:TornadoFill",
    "aliases": [
      "remix",
      "weather:tornado",
      "fill"
    ],
    "caption": "a black background with an airplane flying in the air",
    "colors": []
  },
  {
    "src_svg": "/home/darren/icon-retrieval/icons-dynamic/remix-weather/remix-weather:tornado-line.svg",
    "component_id": "Icon.RemixWeather:TornadoLine",
    "aliases": [
      "remix",
      "weather:tornado",
      "line"
    ],
    "caption": "a black background with an airplane flying in the air",
    "colors": []
  },
  {
    "src_svg": "/home/darren/icon-retrieval/icons-dynamic/remix-weather/remix-weather:typhoon-fill.svg",
    "component_id": "Icon.RemixWeather:TyphoonFill",
    "aliases": [
      "remix",
      "weather:typhoon",
      "fill"
    ],
    "caption": "a black background with an airplane flying in the air",
    "colors": []
  },
  {
    "src_svg": "/home/darren/icon-retrieval/icons-dynamic/remix-weather/remix-weather:typhoon-line.svg",
    "component_id": "Icon.RemixWeather:TyphoonLine",
    "aliases": [
      "remix",
      "weather:typhoon",
      "line"
    ],
    "caption": "a black background with an airplane flying in the air",
    "colors": []
  },
  {
    "src_svg": "/home/darren/icon-retrieval/icons-dynamic/remix-weather/remix-weather:water-percent-fill.svg",
    "component_id": "Icon.RemixWeather:WaterPercentFill",
    "aliases": [
      "remix",
      "weather:water",
      "percent",
      "fill"
    ],
    "caption": "a black background with an airplane flying in the air",
    "colors": []
  },
  {
    "src_svg": "/home/darren/icon-retrieval/icons-dynamic/remix-weather/remix-weather:water-percent-line.svg",
    "component_id": "Icon.RemixWeather:WaterPercentLine",
    "aliases": [
      "remix",
      "weather:water",
      "percent",
      "line"
    ],
    "caption": "a black background with an airplane flying in the air",
    "colors": []
  },
  {
    "src_svg": "/home/darren/icon-retrieval/icons-dynamic/remix-weather/remix-weather:windy-fill.svg",
    "component_id": "Icon.RemixWeather:WindyFill",
    "aliases": [
      "remix",
      "weather:windy",
      "fill"
    ],
    "caption": "a black background with an airplane flying in the air",
    "colors": []
  },
  {
    "src_svg": "/home/darren/icon-retrieval/icons-dynamic/remix-weather/remix-weather:windy-line.svg",
    "component_id": "Icon.RemixWeather:WindyLine",
    "aliases": [
      "remix",
      "weather:windy",
      "line"
    ],
    "caption": "a black background with an airplane flying in the air",
    "colors": []
  }
]