[
  {
    "src_svg": "/home/darren/icon-retrieval/icons-dynamic/remix-editor/remix-editor:a-b.svg",
    "component_id": "Icon.RemixEditor:AB",
    "aliases": [
      "remix",
      "editor:a",
      "b"
    ],
    "caption": "a black background with an airplane flying in the air",
    "colors": []
  },
  {
    "src_svg": "/home/darren/icon-retrieval/icons-dynamic/remix-editor/remix-editor:ai-generate-2.svg",
    "component_id": "Icon.RemixEditor:AiGenerate2",
    "aliases": [
      "remix",
      "editor:ai",
      "generate",
      "2"
    ],
    "caption": "a black background with an airplane flying in the air",
    "colors": []
  },
  {
    "src_svg": "/home/darren/icon-retrieval/icons-dynamic/remix-editor/remix-editor:ai-generate-text.svg",
    "component_id": "Icon.RemixEditor:AiGenerateText",
    "aliases": [
      "remix",
      "editor:ai",
      "generate",
      "text"
    ],
    "caption": "a black background with an airplane flying in the air",
    "colors": []
  },
  {
    "src_svg": "/home/darren/icon-retrieval/icons-dynamic/remix-editor/remix-editor:ai-generate.svg",
    "component_id": "Icon.RemixEditor:AiGenerate",
    "aliases": [
      "remix",
      "editor:ai",
      "generate"
    ],
    "caption": "a black background with an airplane flying in the air",
    "colors": []
  },
  {
    "src_svg": "/home/darren/icon-retrieval/icons-dynamic/remix-editor/remix-editor:ai.svg",
    "component_id": "Icon.RemixEditor:Ai",
    "aliases": [
      "remix",
      "editor:ai"
    ],
    "caption": "a black background with an airplane flying in the air",
    "colors": []
  },
  {
    "src_svg": "/home/darren/icon-retrieval/icons-dynamic/remix-editor/remix-editor:align-bottom.svg",
    "component_id": "Icon.RemixEditor:AlignBottom",
    "aliases": [
      "remix",
      "editor:align",
      "bottom"
    ],
    "caption": "a black background with an airplane flying in the air",
    "colors": []
  },
  {
    "src_svg": "/home/darren/icon-retrieval/icons-dynamic/remix-editor/remix-editor:align-center.svg",
    "component_id": "Icon.RemixEditor:AlignCenter",
    "aliases": [
      "remix",
      "editor:align",
      "center"
    ],
    "caption": "a black background with an airplane flying in the air",
    "colors": []
  },
  {
    "src_svg": "/home/darren/icon-retrieval/icons-dynamic/remix-editor/remix-editor:align-justify.svg",
    "component_id": "Icon.RemixEditor:AlignJustify",
    "aliases": [
      "remix",
      "editor:align",
      "justify"
    ],
    "caption": "a black background with an airplane flying in the air",
    "colors": []
  },
  {
    "src_svg": "/home/darren/icon-retrieval/icons-dynamic/remix-editor/remix-editor:align-left.svg",
    "component_id": "Icon.RemixEditor:AlignLeft",
    "aliases": [
      "remix",
      "editor:align",
      "left"
    ],
    "caption": "a black background with an airplane flying in the air",
    "colors": []
  },
  {
    "src_svg": "/home/darren/icon-retrieval/icons-dynamic/remix-editor/remix-editor:align-right.svg",
    "component_id": "Icon.RemixEditor:AlignRight",
    "aliases": [
      "remix",
      "editor:align",
      "right"
    ],
    "caption": "a black background with an airplane flying in the air",
    "colors": []
  },
  {
    "src_svg": "/home/darren/icon-retrieval/icons-dynamic/remix-editor/remix-editor:align-top.svg",
    "component_id": "Icon.RemixEditor:AlignTop",
    "aliases": [
      "remix",
      "editor:align",
      "top"
    ],
    "caption": "a black background with an airplane flying in the air",
    "colors": []
  },
  {
    "src_svg": "/home/darren/icon-retrieval/icons-dynamic/remix-editor/remix-editor:align-vertically.svg",
    "component_id": "Icon.RemixEditor:AlignVertically",
    "aliases": [
      "remix",
      "editor:align",
      "vertically"
    ],
    "caption": "a black background with an airplane flying in the air",
    "colors": []
  },
  {
    "src_svg": "/home/darren/icon-retrieval/icons-dynamic/remix-editor/remix-editor:asterisk.svg",
    "component_id": "Icon.RemixEditor:Asterisk",
    "aliases": [
      "remix",
      "editor:asterisk"
    ],
    "caption": "a black background with an airplane flying in the air",
    "colors": []
  },
  {
    "src_svg": "/home/darren/icon-retrieval/icons-dynamic/remix-editor/remix-editor:attachment-2.svg",
    "component_id": "Icon.RemixEditor:Attachment2",
    "aliases": [
      "remix",
      "editor:attachment",
      "2"
    ],
    "caption": "a black background with an airplane flying in the air",
    "colors": []
  },
  {
    "src_svg": "/home/darren/icon-retrieval/icons-dynamic/remix-editor/remix-editor:bold.svg",
    "component_id": "Icon.RemixEditor:Bold",
    "aliases": [
      "remix",
      "editor:bold"
    ],
    "caption": "a black background with an airplane flying in the air",
    "colors": []
  },
  {
    "src_svg": "/home/darren/icon-retrieval/icons-dynamic/remix-editor/remix-editor:bring-forward.svg",
    "component_id": "Icon.RemixEditor:BringForward",
    "aliases": [
      "remix",
      "editor:bring",
      "forward"
    ],
    "caption": "a black background with an airplane flying in the air",
    "colors": []
  },
  {
    "src_svg": "/home/darren/icon-retrieval/icons-dynamic/remix-editor/remix-editor:bring-to-front.svg",
    "component_id": "Icon.RemixEditor:BringToFront",
    "aliases": [
      "remix",
      "editor:bring",
      "to",
      "front"
    ],
    "caption": "a black background with an airplane flying in the air",
    "colors": []
  },
  {
    "src_svg": "/home/darren/icon-retrieval/icons-dynamic/remix-editor/remix-editor:calendar-view.svg",
    "component_id": "Icon.RemixEditor:CalendarView",
    "aliases": [
      "remix",
      "editor:calendar",
      "view"
    ],
    "caption": "a black background with an airplane flying in the air",
    "colors": []
  },
  {
    "src_svg": "/home/darren/icon-retrieval/icons-dynamic/remix-editor/remix-editor:carousel-view.svg",
    "component_id": "Icon.RemixEditor:CarouselView",
    "aliases": [
      "remix",
      "editor:carousel",
      "view"
    ],
    "caption": "a black background with an airplane flying in the air",
    "colors": []
  },
  {
    "src_svg": "/home/darren/icon-retrieval/icons-dynamic/remix-editor/remix-editor:code-block.svg",
    "component_id": "Icon.RemixEditor:CodeBlock",
    "aliases": [
      "remix",
      "editor:code",
      "block"
    ],
    "caption": "a black background with an airplane flying in the air",
    "colors": []
  },
  {
    "src_svg": "/home/darren/icon-retrieval/icons-dynamic/remix-editor/remix-editor:code-view.svg",
    "component_id": "Icon.RemixEditor:CodeView",
    "aliases": [
      "remix",
      "editor:code",
      "view"
    ],
    "caption": "a black background with an airplane flying in the air",
    "colors": []
  },
  {
    "src_svg": "/home/darren/icon-retrieval/icons-dynamic/remix-editor/remix-editor:custom-size.svg",
    "component_id": "Icon.RemixEditor:CustomSize",
    "aliases": [
      "remix",
      "editor:custom",
      "size"
    ],
    "caption": "a black background with an airplane flying in the air",
    "colors": []
  },
  {
    "src_svg": "/home/darren/icon-retrieval/icons-dynamic/remix-editor/remix-editor:delete-column.svg",
    "component_id": "Icon.RemixEditor:DeleteColumn",
    "aliases": [
      "remix",
      "editor:delete",
      "column"
    ],
    "caption": "a black background with an airplane flying in the air",
    "colors": []
  },
  {
    "src_svg": "/home/darren/icon-retrieval/icons-dynamic/remix-editor/remix-editor:delete-row.svg",
    "component_id": "Icon.RemixEditor:DeleteRow",
    "aliases": [
      "remix",
      "editor:delete",
      "row"
    ],
    "caption": "a black background with an airplane flying in the air",
    "colors": []
  },
  {
    "src_svg": "/home/darren/icon-retrieval/icons-dynamic/remix-editor/remix-editor:double-quotes-l.svg",
    "component_id": "Icon.RemixEditor:DoubleQuotesL",
    "aliases": [
      "remix",
      "editor:double",
      "quotes",
      "l"
    ],
    "caption": "a black background with an airplane flying in the air",
    "colors": []
  },
  {
    "src_svg": "/home/darren/icon-retrieval/icons-dynamic/remix-editor/remix-editor:double-quotes-r.svg",
    "component_id": "Icon.RemixEditor:DoubleQuotesR",
    "aliases": [
      "remix",
      "editor:double",
      "quotes",
      "r"
    ],
    "caption": "a black background with an airplane flying in the air",
    "colors": []
  },
  {
    "src_svg": "/home/darren/icon-retrieval/icons-dynamic/remix-editor/remix-editor:draggable.svg",
    "component_id": "Icon.RemixEditor:Draggable",
    "aliases": [
      "remix",
      "editor:draggable"
    ],
    "caption": "a black background with an airplane flying in the air",
    "colors": []
  },
  {
    "src_svg": "/home/darren/icon-retrieval/icons-dynamic/remix-editor/remix-editor:dropdown-list.svg",
    "component_id": "Icon.RemixEditor:DropdownList",
    "aliases": [
      "remix",
      "editor:dropdown",
      "list"
    ],
    "caption": "a black background with an airplane flying in the air",
    "colors": []
  },
  {
    "src_svg": "/home/darren/icon-retrieval/icons-dynamic/remix-editor/remix-editor:emphasis-cn.svg",
    "component_id": "Icon.RemixEditor:EmphasisCn",
    "aliases": [
      "remix",
      "editor:emphasis",
      "cn"
    ],
    "caption": "a black background with an airplane flying in the air",
    "colors": []
  },
  {
    "src_svg": "/home/darren/icon-retrieval/icons-dynamic/remix-editor/remix-editor:emphasis.svg",
    "component_id": "Icon.RemixEditor:Emphasis",
    "aliases": [
      "remix",
      "editor:emphasis"
    ],
    "caption": "a black background with an airplane flying in the air",
    "colors": []
  },
  {
    "src_svg": "/home/darren/icon-retrieval/icons-dynamic/remix-editor/remix-editor:english-input.svg",
    "component_id": "Icon.RemixEditor:EnglishInput",
    "aliases": [
      "remix",
      "editor:english",
      "input"
    ],
    "caption": "a black background with an airplane flying in the air",
    "colors": []
  },
  {
    "src_svg": "/home/darren/icon-retrieval/icons-dynamic/remix-editor/remix-editor:flow-chart.svg",
    "component_id": "Icon.RemixEditor:FlowChart",
    "aliases": [
      "remix",
      "editor:flow",
      "chart"
    ],
    "caption": "a black background with an airplane flying in the air",
    "colors": []
  },
  {
    "src_svg": "/home/darren/icon-retrieval/icons-dynamic/remix-editor/remix-editor:focus-mode.svg",
    "component_id": "Icon.RemixEditor:FocusMode",
    "aliases": [
      "remix",
      "editor:focus",
      "mode"
    ],
    "caption": "a black background with an airplane flying in the air",
    "colors": []
  },
  {
    "src_svg": "/home/darren/icon-retrieval/icons-dynamic/remix-editor/remix-editor:font-color.svg",
    "component_id": "Icon.RemixEditor:FontColor",
    "aliases": [
      "remix",
      "editor:font",
      "color"
    ],
    "caption": "a black background with an airplane flying in the air",
    "colors": []
  },
  {
    "src_svg": "/home/darren/icon-retrieval/icons-dynamic/remix-editor/remix-editor:font-family.svg",
    "component_id": "Icon.RemixEditor:FontFamily",
    "aliases": [
      "remix",
      "editor:font",
      "family"
    ],
    "caption": "a black background with an airplane flying in the air",
    "colors": []
  },
  {
    "src_svg": "/home/darren/icon-retrieval/icons-dynamic/remix-editor/remix-editor:font-mono.svg",
    "component_id": "Icon.RemixEditor:FontMono",
    "aliases": [
      "remix",
      "editor:font",
      "mono"
    ],
    "caption": "a black background with an airplane flying in the air",
    "colors": []
  },
  {
    "src_svg": "/home/darren/icon-retrieval/icons-dynamic/remix-editor/remix-editor:font-sans-serif.svg",
    "component_id": "Icon.RemixEditor:FontSansSerif",
    "aliases": [
      "remix",
      "editor:font",
      "sans",
      "serif"
    ],
    "caption": "a black background with an airplane flying in the air",
    "colors": []
  },
  {
    "src_svg": "/home/darren/icon-retrieval/icons-dynamic/remix-editor/remix-editor:font-sans.svg",
    "component_id": "Icon.RemixEditor:FontSans",
    "aliases": [
      "remix",
      "editor:font",
      "sans"
    ],
    "caption": "a black background with an airplane flying in the air",
    "colors": []
  },
  {
    "src_svg": "/home/darren/icon-retrieval/icons-dynamic/remix-editor/remix-editor:font-size-2.svg",
    "component_id": "Icon.RemixEditor:FontSize2",
    "aliases": [
      "remix",
      "editor:font",
      "size",
      "2"
    ],
    "caption": "a black background with an airplane flying in the air",
    "colors": []
  },
  {
    "src_svg": "/home/darren/icon-retrieval/icons-dynamic/remix-editor/remix-editor:font-size-ai.svg",
    "component_id": "Icon.RemixEditor:FontSizeAi",
    "aliases": [
      "remix",
      "editor:font",
      "size",
      "ai"
    ],
    "caption": "a black background with an airplane flying in the air",
    "colors": []
  },
  {
    "src_svg": "/home/darren/icon-retrieval/icons-dynamic/remix-editor/remix-editor:font-size.svg",
    "component_id": "Icon.RemixEditor:FontSize",
    "aliases": [
      "remix",
      "editor:font",
      "size"
    ],
    "caption": "a black background with an airplane flying in the air",
    "colors": []
  },
  {
    "src_svg": "/home/darren/icon-retrieval/icons-dynamic/remix-editor/remix-editor:format-clear.svg",
    "component_id": "Icon.RemixEditor:FormatClear",
    "aliases": [
      "remix",
      "editor:format",
      "clear"
    ],
    "caption": "a black background with an airplane flying in the air",
    "colors": []
  },
  {
    "src_svg": "/home/darren/icon-retrieval/icons-dynamic/remix-editor/remix-editor:formula.svg",
    "component_id": "Icon.RemixEditor:Formula",
    "aliases": [
      "remix",
      "editor:formula"
    ],
    "caption": "a black background with an airplane flying in the air",
    "colors": []
  },
  {
    "src_svg": "/home/darren/icon-retrieval/icons-dynamic/remix-editor/remix-editor:functions.svg",
    "component_id": "Icon.RemixEditor:Functions",
    "aliases": [
      "remix",
      "editor:functions"
    ],
    "caption": "a black background with an airplane flying in the air",
    "colors": []
  },
  {
    "src_svg": "/home/darren/icon-retrieval/icons-dynamic/remix-editor/remix-editor:gallery-view-2.svg",
    "component_id": "Icon.RemixEditor:GalleryView2",
    "aliases": [
      "remix",
      "editor:gallery",
      "view",
      "2"
    ],
    "caption": "a black background with an airplane flying in the air",
    "colors": []
  },
  {
    "src_svg": "/home/darren/icon-retrieval/icons-dynamic/remix-editor/remix-editor:gallery-view.svg",
    "component_id": "Icon.RemixEditor:GalleryView",
    "aliases": [
      "remix",
      "editor:gallery",
      "view"
    ],
    "caption": "a black background with an airplane flying in the air",
    "colors": []
  },
  {
    "src_svg": "/home/darren/icon-retrieval/icons-dynamic/remix-editor/remix-editor:h-1.svg",
    "component_id": "Icon.RemixEditor:H1",
    "aliases": [
      "remix",
      "editor:h",
      "1"
    ],
    "caption": "a black background with an airplane flying in the air",
    "colors": []
  },
  {
    "src_svg": "/home/darren/icon-retrieval/icons-dynamic/remix-editor/remix-editor:h-2.svg",
    "component_id": "Icon.RemixEditor:H2",
    "aliases": [
      "remix",
      "editor:h",
      "2"
    ],
    "caption": "a black background with an airplane flying in the air",
    "colors": []
  },
  {
    "src_svg": "/home/darren/icon-retrieval/icons-dynamic/remix-editor/remix-editor:h-3.svg",
    "component_id": "Icon.RemixEditor:H3",
    "aliases": [
      "remix",
      "editor:h",
      "3"
    ],
    "caption": "a black background with an airplane flying in the air",
    "colors": []
  },
  {
    "src_svg": "/home/darren/icon-retrieval/icons-dynamic/remix-editor/remix-editor:h-4.svg",
    "component_id": "Icon.RemixEditor:H4",
    "aliases": [
      "remix",
      "editor:h",
      "4"
    ],
    "caption": "a black background with an airplane flying in the air",
    "colors": []
  },
  {
    "src_svg": "/home/darren/icon-retrieval/icons-dynamic/remix-editor/remix-editor:h-5.svg",
    "component_id": "Icon.RemixEditor:H5",
    "aliases": [
      "remix",
      "editor:h",
      "5"
    ],
    "caption": "a black background with an airplane flying in the air",
    "colors": []
  },
  {
    "src_svg": "/home/darren/icon-retrieval/icons-dynamic/remix-editor/remix-editor:h-6.svg",
    "component_id": "Icon.RemixEditor:H6",
    "aliases": [
      "remix",
      "editor:h",
      "6"
    ],
    "caption": "a black background with an airplane flying in the air",
    "colors": []
  },
  {
    "src_svg": "/home/darren/icon-retrieval/icons-dynamic/remix-editor/remix-editor:hand.svg",
    "component_id": "Icon.RemixEditor:Hand",
    "aliases": [
      "remix",
      "editor:hand"
    ],
    "caption": "a black background with an airplane flying in the air",
    "colors": []
  },
  {
    "src_svg": "/home/darren/icon-retrieval/icons-dynamic/remix-editor/remix-editor:hashtag.svg",
    "component_id": "Icon.RemixEditor:Hashtag",
    "aliases": [
      "remix",
      "editor:hashtag"
    ],
    "caption": "a black background with an airplane flying in the air",
    "colors": []
  },
  {
    "src_svg": "/home/darren/icon-retrieval/icons-dynamic/remix-editor/remix-editor:heading.svg",
    "component_id": "Icon.RemixEditor:Heading",
    "aliases": [
      "remix",
      "editor:heading"
    ],
    "caption": "a black background with an airplane flying in the air",
    "colors": []
  },
  {
    "src_svg": "/home/darren/icon-retrieval/icons-dynamic/remix-editor/remix-editor:indent-decrease.svg",
    "component_id": "Icon.RemixEditor:IndentDecrease",
    "aliases": [
      "remix",
      "editor:indent",
      "decrease"
    ],
    "caption": "a black background with an airplane flying in the air",
    "colors": []
  },
  {
    "src_svg": "/home/darren/icon-retrieval/icons-dynamic/remix-editor/remix-editor:indent-increase.svg",
    "component_id": "Icon.RemixEditor:IndentIncrease",
    "aliases": [
      "remix",
      "editor:indent",
      "increase"
    ],
    "caption": "a black background with an airplane flying in the air",
    "colors": []
  },
  {
    "src_svg": "/home/darren/icon-retrieval/icons-dynamic/remix-editor/remix-editor:info-i.svg",
    "component_id": "Icon.RemixEditor:InfoI",
    "aliases": [
      "remix",
      "editor:info",
      "i"
    ],
    "caption": "a black background with an airplane flying in the air",
    "colors": []
  },
  {
    "src_svg": "/home/darren/icon-retrieval/icons-dynamic/remix-editor/remix-editor:input-cursor-move.svg",
    "component_id": "Icon.RemixEditor:InputCursorMove",
    "aliases": [
      "remix",
      "editor:input",
      "cursor",
      "move"
    ],
    "caption": "a black background with an airplane flying in the air",
    "colors": []
  },
  {
    "src_svg": "/home/darren/icon-retrieval/icons-dynamic/remix-editor/remix-editor:input-field.svg",
    "component_id": "Icon.RemixEditor:InputField",
    "aliases": [
      "remix",
      "editor:input",
      "field"
    ],
    "caption": "a black background with an airplane flying in the air",
    "colors": []
  },
  {
    "src_svg": "/home/darren/icon-retrieval/icons-dynamic/remix-editor/remix-editor:insert-column-left.svg",
    "component_id": "Icon.RemixEditor:InsertColumnLeft",
    "aliases": [
      "remix",
      "editor:insert",
      "column",
      "left"
    ],
    "caption": "a black background with an airplane flying in the air",
    "colors": []
  },
  {
    "src_svg": "/home/darren/icon-retrieval/icons-dynamic/remix-editor/remix-editor:insert-column-right.svg",
    "component_id": "Icon.RemixEditor:InsertColumnRight",
    "aliases": [
      "remix",
      "editor:insert",
      "column",
      "right"
    ],
    "caption": "a black background with an airplane flying in the air",
    "colors": []
  },
  {
    "src_svg": "/home/darren/icon-retrieval/icons-dynamic/remix-editor/remix-editor:insert-row-bottom.svg",
    "component_id": "Icon.RemixEditor:InsertRowBottom",
    "aliases": [
      "remix",
      "editor:insert",
      "row",
      "bottom"
    ],
    "caption": "a black background with an airplane flying in the air",
    "colors": []
  },
  {
    "src_svg": "/home/darren/icon-retrieval/icons-dynamic/remix-editor/remix-editor:insert-row-top.svg",
    "component_id": "Icon.RemixEditor:InsertRowTop",
    "aliases": [
      "remix",
      "editor:insert",
      "row",
      "top"
    ],
    "caption": "a black background with an airplane flying in the air",
    "colors": []
  },
  {
    "src_svg": "/home/darren/icon-retrieval/icons-dynamic/remix-editor/remix-editor:italic.svg",
    "component_id": "Icon.RemixEditor:Italic",
    "aliases": [
      "remix",
      "editor:italic"
    ],
    "caption": "a black background with an airplane flying in the air",
    "colors": []
  },
  {
    "src_svg": "/home/darren/icon-retrieval/icons-dynamic/remix-editor/remix-editor:kanban-view-2.svg",
    "component_id": "Icon.RemixEditor:KanbanView2",
    "aliases": [
      "remix",
      "editor:kanban",
      "view",
      "2"
    ],
    "caption": "a black background with an airplane flying in the air",
    "colors": []
  },
  {
    "src_svg": "/home/darren/icon-retrieval/icons-dynamic/remix-editor/remix-editor:kanban-view.svg",
    "component_id": "Icon.RemixEditor:KanbanView",
    "aliases": [
      "remix",
      "editor:kanban",
      "view"
    ],
    "caption": "a black background with an airplane flying in the air",
    "colors": []
  },
  {
    "src_svg": "/home/darren/icon-retrieval/icons-dynamic/remix-editor/remix-editor:letter-spacing-2.svg",
    "component_id": "Icon.RemixEditor:LetterSpacing2",
    "aliases": [
      "remix",
      "editor:letter",
      "spacing",
      "2"
    ],
    "caption": "a black background with an airplane flying in the air",
    "colors": []
  },
  {
    "src_svg": "/home/darren/icon-retrieval/icons-dynamic/remix-editor/remix-editor:line-height-2.svg",
    "component_id": "Icon.RemixEditor:LineHeight2",
    "aliases": [
      "remix",
      "editor:line",
      "height",
      "2"
    ],
    "caption": "a black background with an airplane flying in the air",
    "colors": []
  },
  {
    "src_svg": "/home/darren/icon-retrieval/icons-dynamic/remix-editor/remix-editor:line-height.svg",
    "component_id": "Icon.RemixEditor:LineHeight",
    "aliases": [
      "remix",
      "editor:line",
      "height"
    ],
    "caption": "a black background with an airplane flying in the air",
    "colors": []
  },
  {
    "src_svg": "/home/darren/icon-retrieval/icons-dynamic/remix-editor/remix-editor:link-m.svg",
    "component_id": "Icon.RemixEditor:LinkM",
    "aliases": [
      "remix",
      "editor:link",
      "m"
    ],
    "caption": "a black background with an airplane flying in the air",
    "colors": []
  },
  {
    "src_svg": "/home/darren/icon-retrieval/icons-dynamic/remix-editor/remix-editor:link-unlink-m.svg",
    "component_id": "Icon.RemixEditor:LinkUnlinkM",
    "aliases": [
      "remix",
      "editor:link",
      "unlink",
      "m"
    ],
    "caption": "a black background with an airplane flying in the air",
    "colors": []
  },
  {
    "src_svg": "/home/darren/icon-retrieval/icons-dynamic/remix-editor/remix-editor:link-unlink.svg",
    "component_id": "Icon.RemixEditor:LinkUnlink",
    "aliases": [
      "remix",
      "editor:link",
      "unlink"
    ],
    "caption": "a black background with an airplane flying in the air",
    "colors": []
  },
  {
    "src_svg": "/home/darren/icon-retrieval/icons-dynamic/remix-editor/remix-editor:link.svg",
    "component_id": "Icon.RemixEditor:Link",
    "aliases": [
      "remix",
      "editor:link"
    ],
    "caption": "a black background with an airplane flying in the air",
    "colors": []
  },
  {
    "src_svg": "/home/darren/icon-retrieval/icons-dynamic/remix-editor/remix-editor:list-check-2.svg",
    "component_id": "Icon.RemixEditor:ListCheck2",
    "aliases": [
      "remix",
      "editor:list",
      "check",
      "2"
    ],
    "caption": "a black background with an airplane flying in the air",
    "colors": []
  },
  {
    "src_svg": "/home/darren/icon-retrieval/icons-dynamic/remix-editor/remix-editor:list-check-3.svg",
    "component_id": "Icon.RemixEditor:ListCheck3",
    "aliases": [
      "remix",
      "editor:list",
      "check",
      "3"
    ],
    "caption": "a black background with an airplane flying in the air",
    "colors": []
  },
  {
    "src_svg": "/home/darren/icon-retrieval/icons-dynamic/remix-editor/remix-editor:list-check.svg",
    "component_id": "Icon.RemixEditor:ListCheck",
    "aliases": [
      "remix",
      "editor:list",
      "check"
    ],
    "caption": "a black background with an airplane flying in the air",
    "colors": []
  },
  {
    "src_svg": "/home/darren/icon-retrieval/icons-dynamic/remix-editor/remix-editor:list-indefinite.svg",
    "component_id": "Icon.RemixEditor:ListIndefinite",
    "aliases": [
      "remix",
      "editor:list",
      "indefinite"
    ],
    "caption": "a black background with an airplane flying in the air",
    "colors": []
  },
  {
    "src_svg": "/home/darren/icon-retrieval/icons-dynamic/remix-editor/remix-editor:list-ordered-2.svg",
    "component_id": "Icon.RemixEditor:ListOrdered2",
    "aliases": [
      "remix",
      "editor:list",
      "ordered",
      "2"
    ],
    "caption": "a black background with an airplane flying in the air",
    "colors": []
  },
  {
    "src_svg": "/home/darren/icon-retrieval/icons-dynamic/remix-editor/remix-editor:list-ordered.svg",
    "component_id": "Icon.RemixEditor:ListOrdered",
    "aliases": [
      "remix",
      "editor:list",
      "ordered"
    ],
    "caption": "a black background with an airplane flying in the air",
    "colors": []
  },
  {
    "src_svg": "/home/darren/icon-retrieval/icons-dynamic/remix-editor/remix-editor:list-radio.svg",
    "component_id": "Icon.RemixEditor:ListRadio",
    "aliases": [
      "remix",
      "editor:list",
      "radio"
    ],
    "caption": "a black background with an airplane flying in the air",
    "colors": []
  },
  {
    "src_svg": "/home/darren/icon-retrieval/icons-dynamic/remix-editor/remix-editor:list-unordered.svg",
    "component_id": "Icon.RemixEditor:ListUnordered",
    "aliases": [
      "remix",
      "editor:list",
      "unordered"
    ],
    "caption": "a black background with an airplane flying in the air",
    "colors": []
  },
  {
    "src_svg": "/home/darren/icon-retrieval/icons-dynamic/remix-editor/remix-editor:list-view.svg",
    "component_id": "Icon.RemixEditor:ListView",
    "aliases": [
      "remix",
      "editor:list",
      "view"
    ],
    "caption": "a black background with an airplane flying in the air",
    "colors": []
  },
  {
    "src_svg": "/home/darren/icon-retrieval/icons-dynamic/remix-editor/remix-editor:merge-cells-horizontal.svg",
    "component_id": "Icon.RemixEditor:MergeCellsHorizontal",
    "aliases": [
      "remix",
      "editor:merge",
      "cells",
      "horizontal"
    ],
    "caption": "a black background with an airplane flying in the air",
    "colors": []
  },
  {
    "src_svg": "/home/darren/icon-retrieval/icons-dynamic/remix-editor/remix-editor:merge-cells-vertical.svg",
    "component_id": "Icon.RemixEditor:MergeCellsVertical",
    "aliases": [
      "remix",
      "editor:merge",
      "cells",
      "vertical"
    ],
    "caption": "a black background with an airplane flying in the air",
    "colors": []
  },
  {
    "src_svg": "/home/darren/icon-retrieval/icons-dynamic/remix-editor/remix-editor:mind-map.svg",
    "component_id": "Icon.RemixEditor:MindMap",
    "aliases": [
      "remix",
      "editor:mind",
      "map"
    ],
    "caption": "a black background with an airplane flying in the air",
    "colors": []
  },
  {
    "src_svg": "/home/darren/icon-retrieval/icons-dynamic/remix-editor/remix-editor:node-tree.svg",
    "component_id": "Icon.RemixEditor:NodeTree",
    "aliases": [
      "remix",
      "editor:node",
      "tree"
    ],
    "caption": "a black background with an airplane flying in the air",
    "colors": []
  },
  {
    "src_svg": "/home/darren/icon-retrieval/icons-dynamic/remix-editor/remix-editor:number-0.svg",
    "component_id": "Icon.RemixEditor:Number0",
    "aliases": [
      "remix",
      "editor:number",
      "0"
    ],
    "caption": "a black background with an airplane flying in the air",
    "colors": []
  },
  {
    "src_svg": "/home/darren/icon-retrieval/icons-dynamic/remix-editor/remix-editor:number-1.svg",
    "component_id": "Icon.RemixEditor:Number1",
    "aliases": [
      "remix",
      "editor:number",
      "1"
    ],
    "caption": "a black background with an airplane flying in the air",
    "colors": []
  },
  {
    "src_svg": "/home/darren/icon-retrieval/icons-dynamic/remix-editor/remix-editor:number-2.svg",
    "component_id": "Icon.RemixEditor:Number2",
    "aliases": [
      "remix",
      "editor:number",
      "2"
    ],
    "caption": "a black background with an airplane flying in the air",
    "colors": []
  },
  {
    "src_svg": "/home/darren/icon-retrieval/icons-dynamic/remix-editor/remix-editor:number-3.svg",
    "component_id": "Icon.RemixEditor:Number3",
    "aliases": [
      "remix",
      "editor:number",
      "3"
    ],
    "caption": "a black background with an airplane flying in the air",
    "colors": []
  },
  {
    "src_svg": "/home/darren/icon-retrieval/icons-dynamic/remix-editor/remix-editor:number-4.svg",
    "component_id": "Icon.RemixEditor:Number4",
    "aliases": [
      "remix",
      "editor:number",
      "4"
    ],
    "caption": "a black background with an airplane flying in the air",
    "colors": []
  },
  {
    "src_svg": "/home/darren/icon-retrieval/icons-dynamic/remix-editor/remix-editor:number-5.svg",
    "component_id": "Icon.RemixEditor:Number5",
    "aliases": [
      "remix",
      "editor:number",
      "5"
    ],
    "caption": "a black background with an airplane flying in the air",
    "colors": []
  },
  {
    "src_svg": "/home/darren/icon-retrieval/icons-dynamic/remix-editor/remix-editor:number-6.svg",
    "component_id": "Icon.RemixEditor:Number6",
    "aliases": [
      "remix",
      "editor:number",
      "6"
    ],
    "caption": "a black background with an airplane flying in the air",
    "colors": []
  },
  {
    "src_svg": "/home/darren/icon-retrieval/icons-dynamic/remix-editor/remix-editor:number-7.svg",
    "component_id": "Icon.RemixEditor:Number7",
    "aliases": [
      "remix",
      "editor:number",
      "7"
    ],
    "caption": "a black background with an airplane flying in the air",
    "colors": []
  },
  {
    "src_svg": "/home/darren/icon-retrieval/icons-dynamic/remix-editor/remix-editor:number-8.svg",
    "component_id": "Icon.RemixEditor:Number8",
    "aliases": [
      "remix",
      "editor:number",
      "8"
    ],
    "caption": "a black background with an airplane flying in the air",
    "colors": []
  },
  {
    "src_svg": "/home/darren/icon-retrieval/icons-dynamic/remix-editor/remix-editor:number-9.svg",
    "component_id": "Icon.RemixEditor:Number9",
    "aliases": [
      "remix",
      "editor:number",
      "9"
    ],
    "caption": "a black background with an airplane flying in the air",
    "colors": []
  },
  {
    "src_svg": "/home/darren/icon-retrieval/icons-dynamic/remix-editor/remix-editor:omega.svg",
    "component_id": "Icon.RemixEditor:Omega",
    "aliases": [
      "remix",
      "editor:omega"
    ],
    "caption": "a black background with an airplane flying in the air",
    "colors": []
  },
  {
    "src_svg": "/home/darren/icon-retrieval/icons-dynamic/remix-editor/remix-editor:organization-chart.svg",
    "component_id": "Icon.RemixEditor:OrganizationChart",
    "aliases": [
      "remix",
      "editor:organization",
      "chart"
    ],
    "caption": "a black background with an airplane flying in the air",
    "colors": []
  },
  {
    "src_svg": "/home/darren/icon-retrieval/icons-dynamic/remix-editor/remix-editor:overline.svg",
    "component_id": "Icon.RemixEditor:Overline",
    "aliases": [
      "remix",
      "editor:overline"
    ],
    "caption": "a black background with an airplane flying in the air",
    "colors": []
  },
  {
    "src_svg": "/home/darren/icon-retrieval/icons-dynamic/remix-editor/remix-editor:page-separator.svg",
    "component_id": "Icon.RemixEditor:PageSeparator",
    "aliases": [
      "remix",
      "editor:page",
      "separator"
    ],
    "caption": "a black background with an airplane flying in the air",
    "colors": []
  },
  {
    "src_svg": "/home/darren/icon-retrieval/icons-dynamic/remix-editor/remix-editor:paragraph.svg",
    "component_id": "Icon.RemixEditor:Paragraph",
    "aliases": [
      "remix",
      "editor:paragraph"
    ],
    "caption": "a black background with an airplane flying in the air",
    "colors": []
  },
  {
    "src_svg": "/home/darren/icon-retrieval/icons-dynamic/remix-editor/remix-editor:pinyin-input.svg",
    "component_id": "Icon.RemixEditor:PinyinInput",
    "aliases": [
      "remix",
      "editor:pinyin",
      "input"
    ],
    "caption": "a black background with an airplane flying in the air",
    "colors": []
  },
  {
    "src_svg": "/home/darren/icon-retrieval/icons-dynamic/remix-editor/remix-editor:question-mark.svg",
    "component_id": "Icon.RemixEditor:QuestionMark",
    "aliases": [
      "remix",
      "editor:question",
      "mark"
    ],
    "caption": "a black background with an airplane flying in the air",
    "colors": []
  },
  {
    "src_svg": "/home/darren/icon-retrieval/icons-dynamic/remix-editor/remix-editor:quote-text.svg",
    "component_id": "Icon.RemixEditor:QuoteText",
    "aliases": [
      "remix",
      "editor:quote",
      "text"
    ],
    "caption": "a black background with an airplane flying in the air",
    "colors": []
  },
  {
    "src_svg": "/home/darren/icon-retrieval/icons-dynamic/remix-editor/remix-editor:rounded-corner.svg",
    "component_id": "Icon.RemixEditor:RoundedCorner",
    "aliases": [
      "remix",
      "editor:rounded",
      "corner"
    ],
    "caption": "a black background with an airplane flying in the air",
    "colors": []
  },
  {
    "src_svg": "/home/darren/icon-retrieval/icons-dynamic/remix-editor/remix-editor:send-backward.svg",
    "component_id": "Icon.RemixEditor:SendBackward",
    "aliases": [
      "remix",
      "editor:send",
      "backward"
    ],
    "caption": "a black background with an airplane flying in the air",
    "colors": []
  },
  {
    "src_svg": "/home/darren/icon-retrieval/icons-dynamic/remix-editor/remix-editor:send-to-back.svg",
    "component_id": "Icon.RemixEditor:SendToBack",
    "aliases": [
      "remix",
      "editor:send",
      "to",
      "back"
    ],
    "caption": "a black background with an airplane flying in the air",
    "colors": []
  },
  {
    "src_svg": "/home/darren/icon-retrieval/icons-dynamic/remix-editor/remix-editor:separator.svg",
    "component_id": "Icon.RemixEditor:Separator",
    "aliases": [
      "remix",
      "editor:separator"
    ],
    "caption": "a black background with an airplane flying in the air",
    "colors": []
  },
  {
    "src_svg": "/home/darren/icon-retrieval/icons-dynamic/remix-editor/remix-editor:single-quotes-l.svg",
    "component_id": "Icon.RemixEditor:SingleQuotesL",
    "aliases": [
      "remix",
      "editor:single",
      "quotes",
      "l"
    ],
    "caption": "a black background with an airplane flying in the air",
    "colors": []
  },
  {
    "src_svg": "/home/darren/icon-retrieval/icons-dynamic/remix-editor/remix-editor:single-quotes-r.svg",
    "component_id": "Icon.RemixEditor:SingleQuotesR",
    "aliases": [
      "remix",
      "editor:single",
      "quotes",
      "r"
    ],
    "caption": "a black background with an airplane flying in the air",
    "colors": []
  },
  {
    "src_svg": "/home/darren/icon-retrieval/icons-dynamic/remix-editor/remix-editor:sketching.svg",
    "component_id": "Icon.RemixEditor:Sketching",
    "aliases": [
      "remix",
      "editor:sketching"
    ],
    "caption": "a black background with an airplane flying in the air",
    "colors": []
  },
  {
    "src_svg": "/home/darren/icon-retrieval/icons-dynamic/remix-editor/remix-editor:slash-commands-2.svg",
    "component_id": "Icon.RemixEditor:SlashCommands2",
    "aliases": [
      "remix",
      "editor:slash",
      "commands",
      "2"
    ],
    "caption": "a black background with an airplane flying in the air",
    "colors": []
  },
  {
    "src_svg": "/home/darren/icon-retrieval/icons-dynamic/remix-editor/remix-editor:slash-commands.svg",
    "component_id": "Icon.RemixEditor:SlashCommands",
    "aliases": [
      "remix",
      "editor:slash",
      "commands"
    ],
    "caption": "a black background with an airplane flying in the air",
    "colors": []
  },
  {
    "src_svg": "/home/darren/icon-retrieval/icons-dynamic/remix-editor/remix-editor:slideshow-view.svg",
    "component_id": "Icon.RemixEditor:SlideshowView",
    "aliases": [
      "remix",
      "editor:slideshow",
      "view"
    ],
    "caption": "a black background with an airplane flying in the air",
    "colors": []
  },
  {
    "src_svg": "/home/darren/icon-retrieval/icons-dynamic/remix-editor/remix-editor:sort-alphabet-asc.svg",
    "component_id": "Icon.RemixEditor:SortAlphabetAsc",
    "aliases": [
      "remix",
      "editor:sort",
      "alphabet",
      "asc"
    ],
    "caption": "a black background with an airplane flying in the air",
    "colors": []
  },
  {
    "src_svg": "/home/darren/icon-retrieval/icons-dynamic/remix-editor/remix-editor:sort-alphabet-desc.svg",
    "component_id": "Icon.RemixEditor:SortAlphabetDesc",
    "aliases": [
      "remix",
      "editor:sort",
      "alphabet",
      "desc"
    ],
    "caption": "a black background with an airplane flying in the air",
    "colors": []
  },
  {
    "src_svg": "/home/darren/icon-retrieval/icons-dynamic/remix-editor/remix-editor:sort-asc.svg",
    "component_id": "Icon.RemixEditor:SortAsc",
    "aliases": [
      "remix",
      "editor:sort",
      "asc"
    ],
    "caption": "a black background with an airplane flying in the air",
    "colors": []
  },
  {
    "src_svg": "/home/darren/icon-retrieval/icons-dynamic/remix-editor/remix-editor:sort-desc.svg",
    "component_id": "Icon.RemixEditor:SortDesc",
    "aliases": [
      "remix",
      "editor:sort",
      "desc"
    ],
    "caption": "a black background with an airplane flying in the air",
    "colors": []
  },
  {
    "src_svg": "/home/darren/icon-retrieval/icons-dynamic/remix-editor/remix-editor:sort-number-asc.svg",
    "component_id": "Icon.RemixEditor:SortNumberAsc",
    "aliases": [
      "remix",
      "editor:sort",
      "number",
      "asc"
    ],
    "caption": "a black background with an airplane flying in the air",
    "colors": []
  },
  {
    "src_svg": "/home/darren/icon-retrieval/icons-dynamic/remix-editor/remix-editor:sort-number-desc.svg",
    "component_id": "Icon.RemixEditor:SortNumberDesc",
    "aliases": [
      "remix",
      "editor:sort",
      "number",
      "desc"
    ],
    "caption": "a black background with an airplane flying in the air",
    "colors": []
  },
  {
    "src_svg": "/home/darren/icon-retrieval/icons-dynamic/remix-editor/remix-editor:space.svg",
    "component_id": "Icon.RemixEditor:Space",
    "aliases": [
      "remix",
      "editor:space"
    ],
    "caption": "a black background with an airplane flying in the air",
    "colors": []
  },
  {
    "src_svg": "/home/darren/icon-retrieval/icons-dynamic/remix-editor/remix-editor:split-cells-horizontal.svg",
    "component_id": "Icon.RemixEditor:SplitCellsHorizontal",
    "aliases": [
      "remix",
      "editor:split",
      "cells",
      "horizontal"
    ],
    "caption": "a black background with an airplane flying in the air",
    "colors": []
  },
  {
    "src_svg": "/home/darren/icon-retrieval/icons-dynamic/remix-editor/remix-editor:split-cells-vertical.svg",
    "component_id": "Icon.RemixEditor:SplitCellsVertical",
    "aliases": [
      "remix",
      "editor:split",
      "cells",
      "vertical"
    ],
    "caption": "a black background with an airplane flying in the air",
    "colors": []
  },
  {
    "src_svg": "/home/darren/icon-retrieval/icons-dynamic/remix-editor/remix-editor:square-root.svg",
    "component_id": "Icon.RemixEditor:SquareRoot",
    "aliases": [
      "remix",
      "editor:square",
      "root"
    ],
    "caption": "a black background with an airplane flying in the air",
    "colors": []
  },
  {
    "src_svg": "/home/darren/icon-retrieval/icons-dynamic/remix-editor/remix-editor:stacked-view.svg",
    "component_id": "Icon.RemixEditor:StackedView",
    "aliases": [
      "remix",
      "editor:stacked",
      "view"
    ],
    "caption": "a black background with an airplane flying in the air",
    "colors": []
  },
  {
    "src_svg": "/home/darren/icon-retrieval/icons-dynamic/remix-editor/remix-editor:strikethrough-2.svg",
    "component_id": "Icon.RemixEditor:Strikethrough2",
    "aliases": [
      "remix",
      "editor:strikethrough",
      "2"
    ],
    "caption": "a black background with an airplane flying in the air",
    "colors": []
  },
  {
    "src_svg": "/home/darren/icon-retrieval/icons-dynamic/remix-editor/remix-editor:strikethrough.svg",
    "component_id": "Icon.RemixEditor:Strikethrough",
    "aliases": [
      "remix",
      "editor:strikethrough"
    ],
    "caption": "a black background with an airplane flying in the air",
    "colors": []
  },
  {
    "src_svg": "/home/darren/icon-retrieval/icons-dynamic/remix-editor/remix-editor:subscript-2.svg",
    "component_id": "Icon.RemixEditor:Subscript2",
    "aliases": [
      "remix",
      "editor:subscript",
      "2"
    ],
    "caption": "a black background with an airplane flying in the air",
    "colors": []
  },
  {
    "src_svg": "/home/darren/icon-retrieval/icons-dynamic/remix-editor/remix-editor:subscript.svg",
    "component_id": "Icon.RemixEditor:Subscript",
    "aliases": [
      "remix",
      "editor:subscript"
    ],
    "caption": "a black background with an airplane flying in the air",
    "colors": []
  },
  {
    "src_svg": "/home/darren/icon-retrieval/icons-dynamic/remix-editor/remix-editor:superscript-2.svg",
    "component_id": "Icon.RemixEditor:Superscript2",
    "aliases": [
      "remix",
      "editor:superscript",
      "2"
    ],
    "caption": "a black background with an airplane flying in the air",
    "colors": []
  },
  {
    "src_svg": "/home/darren/icon-retrieval/icons-dynamic/remix-editor/remix-editor:superscript.svg",
    "component_id": "Icon.RemixEditor:Superscript",
    "aliases": [
      "remix",
      "editor:superscript"
    ],
    "caption": "a black background with an airplane flying in the air",
    "colors": []
  },
  {
    "src_svg": "/home/darren/icon-retrieval/icons-dynamic/remix-editor/remix-editor:table-2.svg",
    "component_id": "Icon.RemixEditor:Table2",
    "aliases": [
      "remix",
      "editor:table",
      "2"
    ],
    "caption": "a black background with an airplane flying in the air",
    "colors": []
  },
  {
    "src_svg": "/home/darren/icon-retrieval/icons-dynamic/remix-editor/remix-editor:table-3.svg",
    "component_id": "Icon.RemixEditor:Table3",
    "aliases": [
      "remix",
      "editor:table",
      "3"
    ],
    "caption": "a black background with an airplane flying in the air",
    "colors": []
  },
  {
    "src_svg": "/home/darren/icon-retrieval/icons-dynamic/remix-editor/remix-editor:table-view.svg",
    "component_id": "Icon.RemixEditor:TableView",
    "aliases": [
      "remix",
      "editor:table",
      "view"
    ],
    "caption": "a black background with an airplane flying in the air",
    "colors": []
  },
  {
    "src_svg": "/home/darren/icon-retrieval/icons-dynamic/remix-editor/remix-editor:text-block.svg",
    "component_id": "Icon.RemixEditor:TextBlock",
    "aliases": [
      "remix",
      "editor:text",
      "block"
    ],
    "caption": "a black background with an airplane flying in the air",
    "colors": []
  },
  {
    "src_svg": "/home/darren/icon-retrieval/icons-dynamic/remix-editor/remix-editor:text-direction-l.svg",
    "component_id": "Icon.RemixEditor:TextDirectionL",
    "aliases": [
      "remix",
      "editor:text",
      "direction",
      "l"
    ],
    "caption": "a black background with an airplane flying in the air",
    "colors": []
  },
  {
    "src_svg": "/home/darren/icon-retrieval/icons-dynamic/remix-editor/remix-editor:text-direction-r.svg",
    "component_id": "Icon.RemixEditor:TextDirectionR",
    "aliases": [
      "remix",
      "editor:text",
      "direction",
      "r"
    ],
    "caption": "a black background with an airplane flying in the air",
    "colors": []
  },
  {
    "src_svg": "/home/darren/icon-retrieval/icons-dynamic/remix-editor/remix-editor:text-snippet.svg",
    "component_id": "Icon.RemixEditor:TextSnippet",
    "aliases": [
      "remix",
      "editor:text",
      "snippet"
    ],
    "caption": "a black background with an airplane flying in the air",
    "colors": []
  },
  {
    "src_svg": "/home/darren/icon-retrieval/icons-dynamic/remix-editor/remix-editor:text-spacing.svg",
    "component_id": "Icon.RemixEditor:TextSpacing",
    "aliases": [
      "remix",
      "editor:text",
      "spacing"
    ],
    "caption": "a black background with an airplane flying in the air",
    "colors": []
  },
  {
    "src_svg": "/home/darren/icon-retrieval/icons-dynamic/remix-editor/remix-editor:text-wrap.svg",
    "component_id": "Icon.RemixEditor:TextWrap",
    "aliases": [
      "remix",
      "editor:text",
      "wrap"
    ],
    "caption": "a black background with an airplane flying in the air",
    "colors": []
  },
  {
    "src_svg": "/home/darren/icon-retrieval/icons-dynamic/remix-editor/remix-editor:text.svg",
    "component_id": "Icon.RemixEditor:Text",
    "aliases": [
      "remix",
      "editor:text"
    ],
    "caption": "a black background with an airplane flying in the air",
    "colors": []
  },
  {
    "src_svg": "/home/darren/icon-retrieval/icons-dynamic/remix-editor/remix-editor:timeline-view.svg",
    "component_id": "Icon.RemixEditor:TimelineView",
    "aliases": [
      "remix",
      "editor:timeline",
      "view"
    ],
    "caption": "a black background with an airplane flying in the air",
    "colors": []
  },
  {
    "src_svg": "/home/darren/icon-retrieval/icons-dynamic/remix-editor/remix-editor:translate-2.svg",
    "component_id": "Icon.RemixEditor:Translate2",
    "aliases": [
      "remix",
      "editor:translate",
      "2"
    ],
    "caption": "a black background with an airplane flying in the air",
    "colors": []
  },
  {
    "src_svg": "/home/darren/icon-retrieval/icons-dynamic/remix-editor/remix-editor:translate-ai-2.svg",
    "component_id": "Icon.RemixEditor:TranslateAi2",
    "aliases": [
      "remix",
      "editor:translate",
      "ai",
      "2"
    ],
    "caption": "a black background with an airplane flying in the air",
    "colors": []
  },
  {
    "src_svg": "/home/darren/icon-retrieval/icons-dynamic/remix-editor/remix-editor:translate-ai.svg",
    "component_id": "Icon.RemixEditor:TranslateAi",
    "aliases": [
      "remix",
      "editor:translate",
      "ai"
    ],
    "caption": "a black background with an airplane flying in the air",
    "colors": []
  },
  {
    "src_svg": "/home/darren/icon-retrieval/icons-dynamic/remix-editor/remix-editor:translate.svg",
    "component_id": "Icon.RemixEditor:Translate",
    "aliases": [
      "remix",
      "editor:translate"
    ],
    "caption": "a black background with an airplane flying in the air",
    "colors": []
  },
  {
    "src_svg": "/home/darren/icon-retrieval/icons-dynamic/remix-editor/remix-editor:underline.svg",
    "component_id": "Icon.RemixEditor:Underline",
    "aliases": [
      "remix",
      "editor:underline"
    ],
    "caption": "a black background with an airplane flying in the air",
    "colors": []
  },
  {
    "src_svg": "/home/darren/icon-retrieval/icons-dynamic/remix-editor/remix-editor:wubi-input.svg",
    "component_id": "Icon.RemixEditor:WubiInput",
    "aliases": [
      "remix",
      "editor:wubi",
      "input"
    ],
    "caption": "a black background with an airplane flying in the air",
    "colors": []
  }
]